emoji_shortname/__init__.py
emoji_shortname-0.1.1.dist-info/LICENSE
emoji_shortname-0.1.1.dist-info/WHEEL
emoji_shortname-0.1.1.dist-info/METADATA
emoji_shortname-0.1.1.dist-info/RECORD
