Metadata-Version: 2.1
Name: emoji-shortname
Version: 0.1.1
Summary: Replace emoji short names with their corresponding emojis.
Home-page: https://github.com/nicholasphair/emoji-shortname
License: MIT
Author: Nick Phair
Requires-Python: >=3.6.2,<4.0.0
Classifier: License :: OSI Approved :: MIT License
Classifier: Programming Language :: Python :: 3
Classifier: Programming Language :: Python :: 3.7
Classifier: Programming Language :: Python :: 3.8
Classifier: Programming Language :: Python :: 3.9
Requires-Dist: Sphinx (>=4.1.0,<5.0.0)
Requires-Dist: emoji (>=1.2.0,<2.0.0)
Requires-Dist: importlib-metadata (>=4.6.1,<5.0.0); python_version >= "3.7" and python_version < "3.8"
Project-URL: Repository, https://github.com/nicholasphair/emoji-shortname
